graphparser/__init__.py
graphparser/parsing.py
graphparser-0.8.4.dist-info/LICENSE
graphparser-0.8.4.dist-info/METADATA
graphparser-0.8.4.dist-info/WHEEL
graphparser-0.8.4.dist-info/top_level.txt
graphparser-0.8.4.dist-info/RECORD
