Metadata-Version: 2.1
Name: graphparser
Version: 0.8.4
Summary: Parses a string of graph data
Home-page: https://github.com/pyprg/graphparser
Author: pyprg
Author-email: pyprg@outlook.com
Project-URL: Bug Tracker, https://github.com/pyprg/graphparser/issues
Classifier: Programming Language :: Python :: 3
Classifier: License :: OSI Approved :: GNU General Public License v3 or later (GPLv3+)
Classifier: Operating System :: OS Independent
Requires-Python: >=3.6
License-File: LICENSE
